Metadata-Version: 2.1
Name: aerics
Version: 0.0.2
Summary: A networking library for multiplayer games.
Home-page: https://github.com/Aermoss/Aerics
Author: Yusuf Rencber
Author-email: yusufrencber546@gmail.com
License: MIT
Platform: UNKNOWN
License-File: LICENSE
